hammad/__init__.py
hammad/_internal.py
hammad/_main.py
hammad/py.typed
hammad/types.py
hammad/cache/__init__.py
hammad/cache/base_cache.py
hammad/cache/cache.py
hammad/cache/decorators.py
hammad/cache/file_cache.py
hammad/cache/ttl_cache.py
hammad/cli/__init__.py
hammad/cli/animations.py
hammad/cli/plugins.py
hammad/cli/styles/__init__.py
hammad/cli/styles/settings.py
hammad/cli/styles/types.py
hammad/cli/styles/utils.py
hammad/data/__init__.py
hammad/data/collections/__init__.py
hammad/data/collections/collection.py
hammad/data/collections/indexes/__init__.py
hammad/data/collections/indexes/qdrant/__init__.py
hammad/data/collections/indexes/qdrant/index.py
hammad/data/collections/indexes/qdrant/settings.py
hammad/data/collections/indexes/qdrant/utils.py
hammad/data/collections/indexes/tantivy/__init__.py
hammad/data/collections/indexes/tantivy/index.py
hammad/data/collections/indexes/tantivy/settings.py
hammad/data/collections/indexes/tantivy/utils.py
hammad/data/configurations/__init__.py
hammad/data/configurations/configuration.py
hammad/data/models/__init__.py
hammad/data/models/fields.py
hammad/data/models/model.py
hammad/data/models/utils.py
hammad/data/models/extensions/__init__.py
hammad/data/models/extensions/pydantic/__init__.py
hammad/data/models/extensions/pydantic/converters.py
hammad/data/sql/__init__.py
hammad/data/sql/database.py
hammad/data/sql/types.py
hammad/data/types/__init__.py
hammad/data/types/file.py
hammad/data/types/text.py
hammad/data/types/multimodal/__init__.py
hammad/data/types/multimodal/audio.py
hammad/data/types/multimodal/image.py
hammad/formatting/__init__.py
hammad/formatting/json/__init__.py
hammad/formatting/json/converters.py
hammad/formatting/text/__init__.py
hammad/formatting/text/converters.py
hammad/formatting/text/markdown.py
hammad/formatting/yaml/__init__.py
hammad/formatting/yaml/converters.py
hammad/genai/__init__.py
hammad/genai/a2a/__init__.py
hammad/genai/a2a/workers.py
hammad/genai/agents/__init__.py
hammad_python-0.0.28.dist-info/METADATA
hammad_python-0.0.28.dist-info/WHEEL
hammad_python-0.0.28.dist-info/licenses/LICENSE
hammad_python-0.0.28.dist-info/RECORD
