Metadata-Version: 2.4
Name: hammad-python
Version: 0.0.28
Author-email: Hammad Saeed <hammadaidev@gmail.com>
License: MIT License
License-File: LICENSE
Requires-Python: >=3.11
Requires-Dist: ddgs>=9.0.0
Requires-Dist: fasta2a>=0.5.0
Requires-Dist: httpx>=0.28.1
Requires-Dist: msgspec>=0.19.0
Requires-Dist: nest-asyncio>=1.6.0
Requires-Dist: pydantic>=2.11.7
Requires-Dist: rich>=14.0.0
Requires-Dist: selectolax>=0.3.31
Requires-Dist: sqlalchemy>=2.0.41
Requires-Dist: tantivy>=0.24.0
Requires-Dist: tenacity>=8.2.3
Requires-Dist: typing-inspect>=0.9.0
Provides-Extra: ai
Requires-Dist: instructor>=1.9.0; extra == 'ai'
Requires-Dist: litellm>=1.73.6; extra == 'ai'
Requires-Dist: qdrant-client>=1.14.3; extra == 'ai'
Provides-Extra: genai
Requires-Dist: fastapi>=0.115.6; extra == 'genai'
Requires-Dist: instructor>=1.9.0; extra == 'genai'
Requires-Dist: litellm>=1.73.6; extra == 'genai'
Requires-Dist: mcp>=1.10.1; extra == 'genai'
Requires-Dist: pydantic-graph>=0.4.2; extra == 'genai'
Requires-Dist: qdrant-client>=1.14.3; extra == 'genai'
Requires-Dist: uvicorn>=0.34.0; extra == 'genai'
Provides-Extra: graph
Requires-Dist: pydantic-graph>=0.4.2; extra == 'graph'
Provides-Extra: mcp
Requires-Dist: mcp>=1.10.1; extra == 'mcp'
Provides-Extra: serve
Requires-Dist: fastapi>=0.115.6; extra == 'serve'
Requires-Dist: uvicorn>=0.34.0; extra == 'serve'
